MANIFEST.in
README.rst
setup.cfg
setup.py
pysitra/__init__.py
pysitra/pysitra_example.py
pysitra/sitra_cli.py
pysitra/test.py
pysitra/trans.py
pysitra/utils.py
pysitra.egg-info/PKG-INFO
pysitra.egg-info/SOURCES.txt
pysitra.egg-info/dependency_links.txt
pysitra.egg-info/entry_points.txt
pysitra.egg-info/not-zip-safe
pysitra.egg-info/requires.txt
pysitra.egg-info/top_level.txt
pysitra/static/24regions_parameters_from_d48.cpg
pysitra/static/24regions_parameters_from_d48.dbf
pysitra/static/24regions_parameters_from_d48.prj
pysitra/static/24regions_parameters_from_d48.qpj
pysitra/static/24regions_parameters_from_d48.shp
pysitra/static/24regions_parameters_from_d48.shx
pysitra/static/24regions_parameters_from_d96.cpg
pysitra/static/24regions_parameters_from_d96.dbf
pysitra/static/24regions_parameters_from_d96.prj
pysitra/static/24regions_parameters_from_d96.qpj
pysitra/static/24regions_parameters_from_d96.shp
pysitra/static/24regions_parameters_from_d96.shx
pysitra/static/3regions_parameters_from_d48.cpg
pysitra/static/3regions_parameters_from_d48.dbf
pysitra/static/3regions_parameters_from_d48.prj
pysitra/static/3regions_parameters_from_d48.qpj
pysitra/static/3regions_parameters_from_d48.shp
pysitra/static/3regions_parameters_from_d48.shx
pysitra/static/3regions_parameters_from_d96.cpg
pysitra/static/3regions_parameters_from_d96.dbf
pysitra/static/3regions_parameters_from_d96.prj
pysitra/static/3regions_parameters_from_d96.qpj
pysitra/static/3regions_parameters_from_d96.shp
pysitra/static/3regions_parameters_from_d96.shx
pysitra/static/7regions_parameters_from_d48.cpg
pysitra/static/7regions_parameters_from_d48.dbf
pysitra/static/7regions_parameters_from_d48.prj
pysitra/static/7regions_parameters_from_d48.qpj
pysitra/static/7regions_parameters_from_d48.shp
pysitra/static/7regions_parameters_from_d48.shx
pysitra/static/7regions_parameters_from_d96.cpg
pysitra/static/7regions_parameters_from_d96.dbf
pysitra/static/7regions_parameters_from_d96.prj
pysitra/static/7regions_parameters_from_d96.qpj
pysitra/static/7regions_parameters_from_d96.shp
pysitra/static/7regions_parameters_from_d96.shx
pysitra/static/triangle_parameters_from_d48.cpg
pysitra/static/triangle_parameters_from_d48.dbf
