Metadata-Version: 1.0
Name: pysitra
Version: 0.3.4
Summary: Python implementation of the most popular slovenian transformation methods (SiTra!)
Home-page: https://github.com/marjanmo/pysitra
Author: Marjan Moderc
Author-email: marjan.moderc@gmail.com
License: MIT
Platform: UNKNOWN
